autoparse/__init__.py
autoparse/_conv.py
autoparse/_lib.py
autoparse/_more_patterns.py
autoparse/_pattern.py
autoparse/find.py
autoparse/pattern.py
autoread/__init__.py
autoread/energy.py
autoread/geom.py
autoread/matrix.py
autoread/par.py
autoread/_zmat/__init__.py
autoread/_zmat/setval.py
autoread/_zmat/vmat.py
autoread/_zmat/zmat.py
autowrite/__init__.py
autowrite/_mat.py
autowrite/geom.py
autowrite/vmat.py
autowrite/zmat.py
ioformat/__init__.py
ioformat/_format.py
ioformat/_string.py
ioformat/pathtools.py
ioformat/phycon.py
ioformat/ptt.py
autoio_base-0.10.0.dist-info/METADATA
autoio_base-0.10.0.dist-info/WHEEL
autoio_base-0.10.0.dist-info/top_level.txt
autoio_base-0.10.0.dist-info/RECORD
